nl2sql/__init__.py
nl2sql/tools/__init__.py
nl2sql/tools/database/__init__.py
nl2sql/tools/database/data.py
nl2sql/tools/database/metadata.py
nl2sql/tools/database/vector.py
nl2sql/tools/resources/prompts/text2sql/context.md
nl2sql/tools/resources/prompts/text2sql/optimizesql.md
nl2sql/tools/resources/prompts/text2sql/references.md
nl2sql/tools/resources/prompts/text2sql/text2sql_agent.md
nl2sql/tools/resources/prompts/text2sql/text2sql_assembly.md
nl2sql/tools/resources/prompts/text2sql/text2sql_oneshot.md
nl2sql/tools/resources/prompts/text2sql/verify.md
nl2sql/tools/resources/sqls/ddl_mysql.sql
nl2sql/tools/resources/sqls/ddl_postgres.sql
nl2sql/tools/text2sql/__init__.py
nl2sql/tools/text2sql/agent.py
nl2sql/tools/text2sql/assembly.py
nl2sql/tools/text2sql/base.py
nl2sql/tools/text2sql/oneshot.py
nl2sql/utils/__init__.py
nl2sql/utils/ai.py
nl2sql/utils/path.py
nl2sql/utils/strings.py
simple_nl2sql-0.4.0.dist-info/METADATA
simple_nl2sql-0.4.0.dist-info/WHEEL
simple_nl2sql-0.4.0.dist-info/top_level.txt
simple_nl2sql-0.4.0.dist-info/RECORD
