Metadata-Version: 2.4
Name: simple-nl2sql
Version: 0.4.0
Summary: A simple implementation of NL2SQL.
Project-URL: Homepage, https://github.com/secretpot/nl2sql
Project-URL: Repository, https://github.com/secretpot/nl2sql
Requires-Python: >=3.12
Requires-Dist: cryptography>=45.0.5
Requires-Dist: deprecated>=1.2.18
Requires-Dist: httpx[socks]>=0.28.1
Requires-Dist: langchain-ollama>=0.3.3
Requires-Dist: langchain-openai>=0.3.21
Requires-Dist: openai-agents>=0.1.0
Requires-Dist: psycopg2-binary>=2.9.10
Requires-Dist: pydantic>=2.11.5
Requires-Dist: pymilvus>=2.5.11
Requires-Dist: pymysql>=1.1.1
Requires-Dist: records>=0.6.0
Requires-Dist: sqlalchemy>=2.0.41
